MANIFEST.in
README.txt
setup.cfg
setup.py
collective/__init__.py
collective.threecolorstheme.egg-info/PKG-INFO
collective.threecolorstheme.egg-info/SOURCES.txt
collective.threecolorstheme.egg-info/dependency_links.txt
collective.threecolorstheme.egg-info/entry_points.txt
collective.threecolorstheme.egg-info/namespace_packages.txt
collective.threecolorstheme.egg-info/not-zip-safe
collective.threecolorstheme.egg-info/requires.txt
collective.threecolorstheme.egg-info/top_level.txt
collective/threecolorstheme/__init__.py
collective/threecolorstheme/config.py
collective/threecolorstheme/configure.zcml
collective/threecolorstheme/interfaces.py
collective/threecolorstheme/overrides.zcml
collective/threecolorstheme/permissions.py
collective/threecolorstheme/phantasyconfig.py
collective/threecolorstheme/profiles.zcml
collective/threecolorstheme/refresh.txt
collective/threecolorstheme/setuphandlers.py
collective/threecolorstheme/skins.zcml
collective/threecolorstheme/tests.py
collective/threecolorstheme/version.txt
collective/threecolorstheme/alternate_skin/alternate_skin.zip
collective/threecolorstheme/alternate_skin/howtouseit.txt
collective/threecolorstheme/alternate_skin/logo.psd
collective/threecolorstheme/browser/__init__.py
collective/threecolorstheme/browser/configure.zcml
collective/threecolorstheme/browser/ddmenuview.py
collective/threecolorstheme/browser/interfaces.py
collective/threecolorstheme/browser/overrides.zcml
collective/threecolorstheme/browser/phantasy_properties.py
collective/threecolorstheme/browser/utils.py
collective/threecolorstheme/browser/viewlets.py
collective/threecolorstheme/browser/javascripts/ddsections.js
collective/threecolorstheme/browser/javascripts/main.js
collective/threecolorstheme/browser/stylesheets/README.txt
collective/threecolorstheme/browser/stylesheets/threecolorstheme.css.dtml
collective/threecolorstheme/browser/stylesheets/threecolorstheme.phantasy.css.pt
collective/threecolorstheme/browser/templates/ddmenusmacros.pt
collective/threecolorstheme/browser/templates/ddmenuswrapper.pt
collective/threecolorstheme/browser/templates/dropdown-sections.pt
collective/threecolorstheme/content/__init__.py
collective/threecolorstheme/content/schema.py
collective/threecolorstheme/content/skin.py
collective/threecolorstheme/ornicart_skin/howtouseit.txt
collective/threecolorstheme/ornicart_skin/logo.psd
