Metadata-Version: 1.0
Name: collective.threecolorstheme
Version: 0.1
Summary: A Phantasy theme variation for Plone, with 3 dynamic colors
Home-page: http://svn.plone.org/products/collective-phantasy
Author: jean-mat Grimaldi
Author-email: jeanmat.grimaldi@gmail.com
License: GPL
Keywords: web zope plone theme
Platform: UNKNOWN
Classifier: Framework :: Plone
Classifier: Programming Language :: Python
Classifier: Topic :: Software Development :: Libraries :: Python Modules
